pulsarfitpy/__init__.py
pulsarfitpy/core.py
pulsarfitpy-0.2.5.dist-info/licenses/LICENSE
pulsarfitpy-0.2.5.dist-info/METADATA
pulsarfitpy-0.2.5.dist-info/WHEEL
pulsarfitpy-0.2.5.dist-info/top_level.txt
pulsarfitpy-0.2.5.dist-info/RECORD
